[
  null,
  null,
  null,
  {
    "clientSoldToItId": 35,
    "color1IdPicked": 1,
    "color1SoldQuantity": 1,
    "color2IdPicked": 0,
    "color2SoldQuantity": 0,
    "color3IdPicked": 0,
    "color3SoldQuantity": 0,
    "color4IdPicked": 0,
    "color4SoldQuantity": 0,
    "confimed": false,
    "date": "1742462905269",
    "idArticle": 3813,
    "nameArticle": "#HALWA TURK  RAWDA 1KG",
    "vid": 3
  },
  null,
  null,
  null,
  null,
  null,
  null,
  null,
  null,
  null,
  null,
  null,
  null,
  null,
  null,
  null,
  null,
  null,
  null,
  null,
  null,
  null,
  null,
  null,
  null,
  null,
  null,
  null,
  null,
  null,
  null,
  null,
  null,
  null,
  null,
  null,
  null,
  null,
  null,
  null,
  null,
  null,
  null,
  null,
  null,
  null,
  null,
  null,
  null,
  null,
  null,
  null,
  null,
  null,
  null,
  null,
  null,
  null,
  null,
  null,
  null,
  null,
  null,
  null,
  null,
  null,
  null,
  null,
  null,
  null,
  null,
  null,
  {
    "clientSoldToItId": 113,
    "color1IdPicked": 93,
    "color1SoldQuantity": 15,
    "color2IdPicked": 0,
    "color2SoldQuantity": 0,
    "color3IdPicked": 0,
    "color3SoldQuantity": 0,
    "color4IdPicked": 0,
    "color4SoldQuantity": 0,
    "confimed": false,
    "date": "1742376266523",
    "idArticle": 829,
    "nameArticle": "chameau",
    "vid": 75
  },
  {
    "clientSoldToItId": 113,
    "color1IdPicked": 93,
    "color1SoldQuantity": 8,
    "color2IdPicked": 0,
    "color2SoldQuantity": 0,
    "color3IdPicked": 0,
    "color3SoldQuantity": 0,
    "color4IdPicked": 0,
    "color4SoldQuantity": 0,
    "confimed": false,
    "date": "1742376365821",
    "idArticle": 848,
    "nameArticle": "toffia",
    "vid": 76
  },
  {
    "clientSoldToItId": 8,
    "color1IdPicked": 93,
    "color1SoldQuantity": 3,
    "color2IdPicked": 0,
    "color2SoldQuantity": 0,
    "color3IdPicked": 0,
    "color3SoldQuantity": 0,
    "color4IdPicked": 0,
    "color4SoldQuantity": 0,
    "confimed": false,
    "date": "1742378512834",
    "idArticle": 872,
    "nameArticle": "ananas",
    "vid": 77
  },
  {
    "clientSoldToItId": 8,
    "color1IdPicked": 93,
    "color1SoldQuantity": 5,
    "color2IdPicked": 0,
    "color2SoldQuantity": 0,
    "color3IdPicked": 0,
    "color3SoldQuantity": 0,
    "color4IdPicked": 0,
    "color4SoldQuantity": 0,
    "confimed": false,
    "date": "1742378527362",
    "idArticle": 1064,
    "nameArticle": "zbib 2 e choix",
    "vid": 78
  },
  {
    "clientSoldToItId": 8,
    "color1IdPicked": 0,
    "color1SoldQuantity": 0,
    "color2IdPicked": 0,
    "color2SoldQuantity": 0,
    "color3IdPicked": 0,
    "color3SoldQuantity": 0,
    "color4IdPicked": 0,
    "color4SoldQuantity": 0,
    "confimed": false,
    "date": "1742378538127",
    "idArticle": 150,
    "nameArticle": "La Skoidra®",
    "vid": 79
  },
  {
    "clientSoldToItId": 8,
    "color1IdPicked": 38,
    "color1SoldQuantity": 1,
    "color2IdPicked": 0,
    "color2SoldQuantity": 0,
    "color3IdPicked": 0,
    "color3SoldQuantity": 0,
    "color4IdPicked": 0,
    "color4SoldQuantity": 0,
    "confimed": false,
    "date": "1742378539921",
    "idArticle": 150,
    "nameArticle": "La Skoidra®",
    "vid": 80
  },
  {
    "clientSoldToItId": 8,
    "color1IdPicked": 1,
    "color1SoldQuantity": 1,
    "color2IdPicked": 0,
    "color2SoldQuantity": 0,
    "color3IdPicked": 0,
    "color3SoldQuantity": 0,
    "color4IdPicked": 0,
    "color4SoldQuantity": 0,
    "confimed": false,
    "date": "1742378550337",
    "idArticle": 3712,
    "nameArticle": "my candy",
    "vid": 81
  },
  {
    "clientSoldToItId": 8,
    "color1IdPicked": 93,
    "color1SoldQuantity": 1,
    "color2IdPicked": 0,
    "color2SoldQuantity": 0,
    "color3IdPicked": 0,
    "color3SoldQuantity": 0,
    "color4IdPicked": 0,
    "color4SoldQuantity": 0,
    "confimed": false,
    "date": "1742378591864",
    "idArticle": 962,
    "nameArticle": "jelly loubia dydo",
    "vid": 82
  },
  {
    "clientSoldToItId": 37,
    "color1IdPicked": 5,
    "color1SoldQuantity": 1,
    "color2IdPicked": 0,
    "color2SoldQuantity": 0,
    "color3IdPicked": 0,
    "color3SoldQuantity": 0,
    "color4IdPicked": 0,
    "color4SoldQuantity": 0,
    "confimed": false,
    "date": "1742379187916",
    "idArticle": 86,
    "nameArticle": "Chiwawa 50 Da®",
    "vid": 83
  },
  {
    "clientSoldToItId": 37,
    "color1IdPicked": 93,
    "color1SoldQuantity": 6,
    "color2IdPicked": 0,
    "color2SoldQuantity": 0,
    "color3IdPicked": 0,
    "color3SoldQuantity": 0,
    "color4IdPicked": 0,
    "color4SoldQuantity": 0,
    "confimed": false,
    "date": "1742379210416",
    "idArticle": 848,
    "nameArticle": "toffia",
    "vid": 84
  },
  {
    "clientSoldToItId": 37,
    "color1IdPicked": 1,
    "color1SoldQuantity": 1,
    "color2IdPicked": 0,
    "color2SoldQuantity": 0,
    "color3IdPicked": 0,
    "color3SoldQuantity": 0,
    "color4IdPicked": 0,
    "color4SoldQuantity": 0,
    "confimed": false,
    "date": "1742379309723",
    "idArticle": 3626,
    "nameArticle": "Vicky Arneb فيكي ارنب",
    "vid": 85
  },
  {
    "clientSoldToItId": 37,
    "color1IdPicked": 27,
    "color1SoldQuantity": 1,
    "color2IdPicked": 0,
    "color2SoldQuantity": 0,
    "color3IdPicked": 0,
    "color3SoldQuantity": 0,
    "color4IdPicked": 0,
    "color4SoldQuantity": 0,
    "confimed": false,
    "date": "1742379365393",
    "idArticle": 61,
    "nameArticle": "Afrah®",
    "vid": 86
  },
  {
    "clientSoldToItId": 37,
    "color1IdPicked": 0,
    "color1SoldQuantity": 0,
    "color2IdPicked": 10,
    "color2SoldQuantity": 1,
    "color3IdPicked": 0,
    "color3SoldQuantity": 0,
    "color4IdPicked": 0,
    "color4SoldQuantity": 0,
    "confimed": false,
    "date": "1742379391184",
    "idArticle": 101,
    "nameArticle": "May Stick®",
    "vid": 87
  },
  {
    "clientSoldToItId": 37,
    "color1IdPicked": 1,
    "color1SoldQuantity": 1,
    "color2IdPicked": 0,
    "color2SoldQuantity": 0,
    "color3IdPicked": 0,
    "color3SoldQuantity": 0,
    "color4IdPicked": 0,
    "color4SoldQuantity": 0,
    "confimed": false,
    "date": "1742379413210",
    "idArticle": 3680,
    "nameArticle": "Florida",
    "vid": 88
  },
  {
    "clientSoldToItId": 37,
    "color1IdPicked": 1,
    "color1SoldQuantity": 2,
    "color2IdPicked": 0,
    "color2SoldQuantity": 0,
    "color3IdPicked": 0,
    "color3SoldQuantity": 0,
    "color4IdPicked": 0,
    "color4SoldQuantity": 0,
    "confimed": false,
    "date": "1742379436845",
    "idArticle": 3717,
    "nameArticle": "freedent",
    "vid": 89
  },
  {
    "clientSoldToItId": 37,
    "color1IdPicked": 0,
    "color1SoldQuantity": 0,
    "color2IdPicked": 0,
    "color2SoldQuantity": 0,
    "color3IdPicked": 0,
    "color3SoldQuantity": 0,
    "color4IdPicked": 0,
    "color4SoldQuantity": 0,
    "confimed": false,
    "date": "1742379455021",
    "idArticle": 3717,
    "nameArticle": "freedent",
    "vid": 90
  },
  {
    "clientSoldToItId": 37,
    "color1IdPicked": 1,
    "color1SoldQuantity": 1,
    "color2IdPicked": 0,
    "color2SoldQuantity": 0,
    "color3IdPicked": 0,
    "color3SoldQuantity": 0,
    "color4IdPicked": 0,
    "color4SoldQuantity": 0,
    "confimed": false,
    "date": "1742379490739",
    "idArticle": 3624,
    "nameArticle": "pupji",
    "vid": 91
  },
  {
    "clientSoldToItId": 37,
    "color1IdPicked": 1,
    "color1SoldQuantity": 1,
    "color2IdPicked": 2,
    "color2SoldQuantity": 1,
    "color3IdPicked": 0,
    "color3SoldQuantity": 0,
    "color4IdPicked": 0,
    "color4SoldQuantity": 0,
    "confimed": false,
    "date": "1742379502994",
    "idArticle": 3713,
    "nameArticle": "bombino",
    "vid": 92
  },
  {
    "clientSoldToItId": 37,
    "color1IdPicked": 12,
    "color1SoldQuantity": 1,
    "color2IdPicked": 0,
    "color2SoldQuantity": 0,
    "color3IdPicked": 0,
    "color3SoldQuantity": 0,
    "color4IdPicked": 0,
    "color4SoldQuantity": 0,
    "confimed": false,
    "date": "1742379528753",
    "idArticle": 68,
    "nameArticle": "Caprice Stick®",
    "vid": 93
  },
  {
    "clientSoldToItId": 37,
    "color1IdPicked": 34,
    "color1SoldQuantity": 1,
    "color2IdPicked": 0,
    "color2SoldQuantity": 0,
    "color3IdPicked": 0,
    "color3SoldQuantity": 0,
    "color4IdPicked": 0,
    "color4SoldQuantity": 0,
    "confimed": false,
    "date": "1742379534948",
    "idArticle": 109,
    "nameArticle": "Schwepsi®",
    "vid": 94
  },
  {
    "clientSoldToItId": 37,
    "color1IdPicked": 24,
    "color1SoldQuantity": 1,
    "color2IdPicked": 0,
    "color2SoldQuantity": 0,
    "color3IdPicked": 0,
    "color3SoldQuantity": 0,
    "color4IdPicked": 0,
    "color4SoldQuantity": 0,
    "confimed": false,
    "date": "1742379557262",
    "idArticle": 92,
    "nameArticle": "Pilpo حارة®",
    "vid": 95
  },
  {
    "clientSoldToItId": 37,
    "color1IdPicked": 24,
    "color1SoldQuantity": 1,
    "color2IdPicked": 0,
    "color2SoldQuantity": 0,
    "color3IdPicked": 0,
    "color3SoldQuantity": 0,
    "color4IdPicked": 0,
    "color4SoldQuantity": 0,
    "confimed": false,
    "date": "1742379574141",
    "idArticle": 74,
    "nameArticle": "May 200®",
    "vid": 96
  },
  {
    "clientSoldToItId": 37,
    "color1IdPicked": 0,
    "color1SoldQuantity": 0,
    "color2IdPicked": 0,
    "color2SoldQuantity": 0,
    "color3IdPicked": 0,
    "color3SoldQuantity": 0,
    "color4IdPicked": 0,
    "color4SoldQuantity": 0,
    "confimed": false,
    "date": "1742379587387",
    "idArticle": 195,
    "nameArticle": "Cap 200®",
    "vid": 97
  },
  {
    "clientSoldToItId": 37,
    "color1IdPicked": 74,
    "color1SoldQuantity": 1,
    "color2IdPicked": 0,
    "color2SoldQuantity": 0,
    "color3IdPicked": 0,
    "color3SoldQuantity": 0,
    "color4IdPicked": 0,
    "color4SoldQuantity": 0,
    "confimed": false,
    "date": "1742379600286",
    "idArticle": 756,
    "nameArticle": "Chwep-Si Cojak®",
    "vid": 98
  },
  {
    "clientSoldToItId": 37,
    "color1IdPicked": 1,
    "color1SoldQuantity": 1,
    "color2IdPicked": 0,
    "color2SoldQuantity": 0,
    "color3IdPicked": 0,
    "color3SoldQuantity": 0,
    "color4IdPicked": 0,
    "color4SoldQuantity": 0,
    "confimed": false,
    "date": "1742379618649",
    "idArticle": 3714,
    "nameArticle": "bolix",
    "vid": 99
  },
  {
    "clientSoldToItId": 119,
    "color1IdPicked": 24,
    "color1SoldQuantity": 2,
    "color2IdPicked": 0,
    "color2SoldQuantity": 0,
    "color3IdPicked": 0,
    "color3SoldQuantity": 0,
    "color4IdPicked": 0,
    "color4SoldQuantity": 0,
    "confimed": false,
    "date": "1742380536840",
    "idArticle": 74,
    "nameArticle": "May 200®",
    "vid": 100
  },
  {
    "clientSoldToItId": 119,
    "color1IdPicked": 74,
    "color1SoldQuantity": 2,
    "color2IdPicked": 0,
    "color2SoldQuantity": 0,
    "color3IdPicked": 0,
    "color3SoldQuantity": 0,
    "color4IdPicked": 0,
    "color4SoldQuantity": 0,
    "confimed": false,
    "date": "1742380551256",
    "idArticle": 791,
    "nameArticle": "Caprice Caramel®",
    "vid": 101
  },
  {
    "clientSoldToItId": 119,
    "color1IdPicked": 24,
    "color1SoldQuantity": 2,
    "color2IdPicked": 0,
    "color2SoldQuantity": 0,
    "color3IdPicked": 0,
    "color3SoldQuantity": 0,
    "color4IdPicked": 0,
    "color4SoldQuantity": 0,
    "confimed": false,
    "date": "1742380675032",
    "idArticle": 74,
    "nameArticle": "May 200®",
    "vid": 102
  },
  {
    "clientSoldToItId": 119,
    "color1IdPicked": 74,
    "color1SoldQuantity": 2,
    "color2IdPicked": 0,
    "color2SoldQuantity": 0,
    "color3IdPicked": 0,
    "color3SoldQuantity": 0,
    "color4IdPicked": 0,
    "color4SoldQuantity": 0,
    "confimed": false,
    "date": "1742380678866",
    "idArticle": 791,
    "nameArticle": "Caprice Caramel®",
    "vid": 103
  },
  {
    "clientSoldToItId": 13,
    "color1IdPicked": 24,
    "color1SoldQuantity": 2,
    "color2IdPicked": 0,
    "color2SoldQuantity": 0,
    "color3IdPicked": 0,
    "color3SoldQuantity": 0,
    "color4IdPicked": 0,
    "color4SoldQuantity": 0,
    "confimed": false,
    "date": "1742380706990",
    "idArticle": 74,
    "nameArticle": "May 200®",
    "vid": 104
  },
  {
    "clientSoldToItId": 13,
    "color1IdPicked": 74,
    "color1SoldQuantity": 2,
    "color2IdPicked": 0,
    "color2SoldQuantity": 0,
    "color3IdPicked": 0,
    "color3SoldQuantity": 0,
    "color4IdPicked": 0,
    "color4SoldQuantity": 0,
    "confimed": false,
    "date": "1742380713145",
    "idArticle": 791,
    "nameArticle": "Caprice Caramel®",
    "vid": 105
  },
  {
    "clientSoldToItId": 4,
    "color1IdPicked": 1,
    "color1SoldQuantity": 1,
    "color2IdPicked": 0,
    "color2SoldQuantity": 0,
    "color3IdPicked": 0,
    "color3SoldQuantity": 0,
    "color4IdPicked": 0,
    "color4SoldQuantity": 0,
    "confimed": false,
    "date": "1742381329133",
    "idArticle": 3626,
    "nameArticle": "Vicky Arneb فيكي ارنب",
    "vid": 106
  },
  {
    "clientSoldToItId": 4,
    "color1IdPicked": 1,
    "color1SoldQuantity": 1,
    "color2IdPicked": 0,
    "color2SoldQuantity": 0,
    "color3IdPicked": 0,
    "color3SoldQuantity": 0,
    "color4IdPicked": 0,
    "color4SoldQuantity": 0,
    "confimed": false,
    "date": "1742381513605",
    "idArticle": 3627,
    "nameArticle": "Vicky ninja",
    "vid": 107
  },
  {
    "clientSoldToItId": 4,
    "color1IdPicked": 1,
    "color1SoldQuantity": 1,
    "color2IdPicked": 0,
    "color2SoldQuantity": 0,
    "color3IdPicked": 0,
    "color3SoldQuantity": 0,
    "color4IdPicked": 0,
    "color4SoldQuantity": 0,
    "confimed": false,
    "date": "1742381576678",
    "idArticle": 3704,
    "nameArticle": "damel presentoire",
    "vid": 108
  },
  {
    "clientSoldToItId": 4,
    "color1IdPicked": 27,
    "color1SoldQuantity": 1,
    "color2IdPicked": 0,
    "color2SoldQuantity": 0,
    "color3IdPicked": 0,
    "color3SoldQuantity": 0,
    "color4IdPicked": 0,
    "color4SoldQuantity": 0,
    "confimed": false,
    "date": "1742381601178",
    "idArticle": 61,
    "nameArticle": "Afrah®",
    "vid": 109
  },
  {
    "clientSoldToItId": 4,
    "color1IdPicked": 24,
    "color1SoldQuantity": 1,
    "color2IdPicked": 0,
    "color2SoldQuantity": 0,
    "color3IdPicked": 0,
    "color3SoldQuantity": 0,
    "color4IdPicked": 0,
    "color4SoldQuantity": 0,
    "confimed": false,
    "date": "1742382348030",
    "idArticle": 92,
    "nameArticle": "Pilpo حارة®",
    "vid": 110
  },
  {
    "clientSoldToItId": 4,
    "color1IdPicked": 93,
    "color1SoldQuantity": 5,
    "color2IdPicked": 0,
    "color2SoldQuantity": 0,
    "color3IdPicked": 0,
    "color3SoldQuantity": 0,
    "color4IdPicked": 0,
    "color4SoldQuantity": 0,
    "confimed": false,
    "date": "1742382411644",
    "idArticle": 948,
    "nameArticle": "hanna nssibti la3ziza sachet",
    "vid": 111
  },
  {
    "clientSoldToItId": 4,
    "color1IdPicked": 62,
    "color1SoldQuantity": 1,
    "color2IdPicked": 0,
    "color2SoldQuantity": 0,
    "color3IdPicked": 0,
    "color3SoldQuantity": 0,
    "color4IdPicked": 0,
    "color4SoldQuantity": 0,
    "confimed": false,
    "date": "1742382438100",
    "idArticle": 819,
    "nameArticle": "cream deployent ghalia",
    "vid": 112
  },
  {
    "clientSoldToItId": 4,
    "color1IdPicked": 52,
    "color1SoldQuantity": 4,
    "color2IdPicked": 0,
    "color2SoldQuantity": 0,
    "color3IdPicked": 0,
    "color3SoldQuantity": 0,
    "color4IdPicked": 0,
    "color4SoldQuantity": 0,
    "confimed": false,
    "date": "1742382487088",
    "idArticle": 513,
    "nameArticle": "Natura Enfent®",
    "vid": 113
  },
  {
    "clientSoldToItId": 4,
    "color1IdPicked": 1,
    "color1SoldQuantity": 2,
    "color2IdPicked": 0,
    "color2SoldQuantity": 0,
    "color3IdPicked": 0,
    "color3SoldQuantity": 0,
    "color4IdPicked": 0,
    "color4SoldQuantity": 0,
    "confimed": false,
    "date": "1742382510055",
    "idArticle": 3635,
    "nameArticle": "swalis",
    "vid": 114
  },
  {
    "clientSoldToItId": 4,
    "color1IdPicked": 0,
    "color1SoldQuantity": 0,
    "color2IdPicked": 0,
    "color2SoldQuantity": 0,
    "color3IdPicked": 0,
    "color3SoldQuantity": 0,
    "color4IdPicked": 0,
    "color4SoldQuantity": 0,
    "confimed": false,
    "date": "1742382564106",
    "idArticle": 362,
    "nameArticle": "Cotex®",
    "vid": 115
  },
  {
    "clientSoldToItId": 4,
    "color1IdPicked": 8,
    "color1SoldQuantity": 3,
    "color2IdPicked": 0,
    "color2SoldQuantity": 0,
    "color3IdPicked": 0,
    "color3SoldQuantity": 0,
    "color4IdPicked": 0,
    "color4SoldQuantity": 0,
    "confimed": false,
    "date": "1742382572967",
    "idArticle": 362,
    "nameArticle": "Cotex®",
    "vid": 116
  },
  {
    "clientSoldToItId": 4,
    "color1IdPicked": 0,
    "color1SoldQuantity": 0,
    "color2IdPicked": 0,
    "color2SoldQuantity": 0,
    "color3IdPicked": 0,
    "color3SoldQuantity": 0,
    "color4IdPicked": 0,
    "color4SoldQuantity": 0,
    "confimed": false,
    "date": "1742382591815",
    "idArticle": 352,
    "nameArticle": "Krish K7 2 Eme Choix®",
    "vid": 117
  },
  {
    "clientSoldToItId": 4,
    "color1IdPicked": 0,
    "color1SoldQuantity": 0,
    "color2IdPicked": 0,
    "color2SoldQuantity": 0,
    "color3IdPicked": 3,
    "color3SoldQuantity": 1,
    "color4IdPicked": 0,
    "color4SoldQuantity": 0,
    "confimed": false,
    "date": "1742382619020",
    "idArticle": 3670,
    "nameArticle": "kriche 1ere choix",
    "vid": 118
  },
  {
    "clientSoldToItId": 4,
    "color1IdPicked": 0,
    "color1SoldQuantity": 0,
    "color2IdPicked": 0,
    "color2SoldQuantity": 0,
    "color3IdPicked": 0,
    "color3SoldQuantity": 0,
    "color4IdPicked": 0,
    "color4SoldQuantity": 0,
    "confimed": false,
    "date": "1742382632740",
    "idArticle": 352,
    "nameArticle": "Krish K7 2 Eme Choix®",
    "vid": 119
  },
  {
    "clientSoldToItId": 4,
    "color1IdPicked": 0,
    "color1SoldQuantity": 0,
    "color2IdPicked": 0,
    "color2SoldQuantity": 0,
    "color3IdPicked": 0,
    "color3SoldQuantity": 0,
    "color4IdPicked": 0,
    "color4SoldQuantity": 0,
    "confimed": false,
    "date": "1742383462609",
    "idArticle": 859,
    "nameArticle": "saco gm",
    "vid": 120
  },
  {
    "clientSoldToItId": 4,
    "color1IdPicked": 0,
    "color1SoldQuantity": 0,
    "color2IdPicked": 0,
    "color2SoldQuantity": 0,
    "color3IdPicked": 0,
    "color3SoldQuantity": 0,
    "color4IdPicked": 0,
    "color4SoldQuantity": 0,
    "confimed": false,
    "date": "1742383467009",
    "idArticle": 860,
    "nameArticle": "saco pm",
    "vid": 121
  },
  {
    "clientSoldToItId": 4,
    "color1IdPicked": 0,
    "color1SoldQuantity": 0,
    "color2IdPicked": 0,
    "color2SoldQuantity": 0,
    "color3IdPicked": 0,
    "color3SoldQuantity": 0,
    "color4IdPicked": 0,
    "color4SoldQuantity": 0,
    "confimed": false,
    "date": "1742383914893",
    "idArticle": 114,
    "nameArticle": "Mamaia®",
    "vid": 122
  },
  {
    "clientSoldToItId": 2,
    "color1IdPicked": 93,
    "color1SoldQuantity": 10,
    "color2IdPicked": 0,
    "color2SoldQuantity": 0,
    "color3IdPicked": 0,
    "color3SoldQuantity": 0,
    "color4IdPicked": 0,
    "color4SoldQuantity": 0,
    "confimed": false,
    "date": "1742384020013",
    "idArticle": 860,
    "nameArticle": "saco pm",
    "vid": 123
  },
  {
    "clientSoldToItId": 2,
    "color1IdPicked": 93,
    "color1SoldQuantity": 5,
    "color2IdPicked": 0,
    "color2SoldQuantity": 0,
    "color3IdPicked": 0,
    "color3SoldQuantity": 0,
    "color4IdPicked": 0,
    "color4SoldQuantity": 0,
    "confimed": false,
    "date": "1742384023931",
    "idArticle": 859,
    "nameArticle": "saco gm",
    "vid": 124
  },
  {
    "clientSoldToItId": 2,
    "color1IdPicked": 0,
    "color1SoldQuantity": 0,
    "color2IdPicked": 36,
    "color2SoldQuantity": 2,
    "color3IdPicked": 0,
    "color3SoldQuantity": 0,
    "color4IdPicked": 0,
    "color4SoldQuantity": 0,
    "confimed": false,
    "date": "1742384037167",
    "idArticle": 114,
    "nameArticle": "Mamaia®",
    "vid": 125
  },
  {
    "clientSoldToItId": 15,
    "color1IdPicked": 152,
    "color1SoldQuantity": 1,
    "color2IdPicked": 0,
    "color2SoldQuantity": 0,
    "color3IdPicked": 0,
    "color3SoldQuantity": 0,
    "color4IdPicked": 0,
    "color4SoldQuantity": 0,
    "confimed": false,
    "date": "1742385060896",
    "idArticle": 1068,
    "nameArticle": "Vicki parapli",
    "vid": 126
  },
  {
    "clientSoldToItId": 15,
    "color1IdPicked": 14,
    "color1SoldQuantity": 1,
    "color2IdPicked": 0,
    "color2SoldQuantity": 0,
    "color3IdPicked": 0,
    "color3SoldQuantity": 0,
    "color4IdPicked": 0,
    "color4SoldQuantity": 0,
    "confimed": false,
    "date": "1742385070990",
    "idArticle": 23,
    "nameArticle": "Gominola",
    "vid": 127
  },
  {
    "clientSoldToItId": 15,
    "color1IdPicked": 8,
    "color1SoldQuantity": 1,
    "color2IdPicked": 0,
    "color2SoldQuantity": 0,
    "color3IdPicked": 0,
    "color3SoldQuantity": 0,
    "color4IdPicked": 0,
    "color4SoldQuantity": 0,
    "confimed": false,
    "date": "1742385093617",
    "idArticle": 215,
    "nameArticle": "Optila Stick 5Da®",
    "vid": 128
  },
  {
    "clientSoldToItId": 15,
    "color1IdPicked": 24,
    "color1SoldQuantity": 1,
    "color2IdPicked": 0,
    "color2SoldQuantity": 0,
    "color3IdPicked": 0,
    "color3SoldQuantity": 0,
    "color4IdPicked": 0,
    "color4SoldQuantity": 0,
    "confimed": false,
    "date": "1742385107684",
    "idArticle": 101,
    "nameArticle": "May Stick®",
    "vid": 129
  },
  {
    "clientSoldToItId": 15,
    "color1IdPicked": 74,
    "color1SoldQuantity": 1,
    "color2IdPicked": 0,
    "color2SoldQuantity": 0,
    "color3IdPicked": 0,
    "color3SoldQuantity": 0,
    "color4IdPicked": 0,
    "color4SoldQuantity": 0,
    "confimed": false,
    "date": "1742385159123",
    "idArticle": 756,
    "nameArticle": "Chwep-Si Cojak®",
    "vid": 130
  },
  {
    "clientSoldToItId": 15,
    "color1IdPicked": 19,
    "color1SoldQuantity": 2,
    "color2IdPicked": 0,
    "color2SoldQuantity": 0,
    "color3IdPicked": 0,
    "color3SoldQuantity": 0,
    "color4IdPicked": 0,
    "color4SoldQuantity": 0,
    "confimed": false,
    "date": "1742385188031",
    "idArticle": 25,
    "nameArticle": "Liya®",
    "vid": 131
  },
  {
    "clientSoldToItId": 15,
    "color1IdPicked": 22,
    "color1SoldQuantity": 1,
    "color2IdPicked": 0,
    "color2SoldQuantity": 0,
    "color3IdPicked": 0,
    "color3SoldQuantity": 0,
    "color4IdPicked": 0,
    "color4SoldQuantity": 0,
    "confimed": false,
    "date": "1742385224092",
    "idArticle": 28,
    "nameArticle": "Cherchel®",
    "vid": 132
  },
  {
    "clientSoldToItId": 15,
    "color1IdPicked": 8,
    "color1SoldQuantity": 6,
    "color2IdPicked": 0,
    "color2SoldQuantity": 0,
    "color3IdPicked": 0,
    "color3SoldQuantity": 0,
    "color4IdPicked": 0,
    "color4SoldQuantity": 0,
    "confimed": false,
    "date": "1742385306393",
    "idArticle": 339,
    "nameArticle": "Signal كبير®",
    "vid": 133
  },
  {
    "clientSoldToItId": 15,
    "color1IdPicked": 0,
    "color1SoldQuantity": 0,
    "color2IdPicked": 0,
    "color2SoldQuantity": 0,
    "color3IdPicked": 3,
    "color3SoldQuantity": 1,
    "color4IdPicked": 0,
    "color4SoldQuantity": 0,
    "confimed": false,
    "date": "1742385403709",
    "idArticle": 3670,
    "nameArticle": "kriche 1ere choix",
    "vid": 134
  },
  {
    "clientSoldToItId": 89,
    "color1IdPicked": 1,
    "color1SoldQuantity": 1,
    "color2IdPicked": 0,
    "color2SoldQuantity": 0,
    "color3IdPicked": 0,
    "color3SoldQuantity": 0,
    "color4IdPicked": 0,
    "color4SoldQuantity": 0,
    "confimed": false,
    "date": "1742459358466",
    "idArticle": 3719,
    "nameArticle": "maruja",
    "vid": 135
  },
  {
    "clientSoldToItId": 104,
    "color1IdPicked": 52,
    "color1SoldQuantity": 1,
    "color2IdPicked": 0,
    "color2SoldQuantity": 0,
    "color3IdPicked": 0,
    "color3SoldQuantity": 0,
    "color4IdPicked": 0,
    "color4SoldQuantity": 0,
    "confimed": false,
    "date": "1742461161989",
    "idArticle": 418,
    "nameArticle": "Snowboll®",
    "vid": 136
  },
  {
    "clientSoldToItId": 91,
    "color1IdPicked": 2,
    "color1SoldQuantity": 10,
    "color2IdPicked": 0,
    "color2SoldQuantity": 0,
    "color3IdPicked": 0,
    "color3SoldQuantity": 0,
    "color4IdPicked": 0,
    "color4SoldQuantity": 0,
    "confimed": false,
    "date": "1742468295350",
    "idArticle": 189,
    "nameArticle": "Excelence®",
    "vid": 137
  },
  {
    "clientSoldToItId": 91,
    "color1IdPicked": 18,
    "color1SoldQuantity": 10,
    "color2IdPicked": 0,
    "color2SoldQuantity": 0,
    "color3IdPicked": 0,
    "color3SoldQuantity": 0,
    "color4IdPicked": 0,
    "color4SoldQuantity": 0,
    "confimed": false,
    "date": "1742468341319",
    "idArticle": 182,
    "nameArticle": "Nice®",
    "vid": 138
  },
  {
    "clientSoldToItId": 91,
    "color1IdPicked": 24,
    "color1SoldQuantity": 1,
    "color2IdPicked": 0,
    "color2SoldQuantity": 0,
    "color3IdPicked": 0,
    "color3SoldQuantity": 0,
    "color4IdPicked": 0,
    "color4SoldQuantity": 0,
    "confimed": false,
    "date": "1742468386766",
    "idArticle": 101,
    "nameArticle": "May Stick®",
    "vid": 139
  },
  {
    "clientSoldToItId": 91,
    "color1IdPicked": 11,
    "color1SoldQuantity": 1,
    "color2IdPicked": 0,
    "color2SoldQuantity": 0,
    "color3IdPicked": 0,
    "color3SoldQuantity": 0,
    "color4IdPicked": 0,
    "color4SoldQuantity": 0,
    "confimed": false,
    "date": "1742468469436",
    "idArticle": 75,
    "nameArticle": "Napolitano®",
    "vid": 140
  },
  {
    "clientSoldToItId": 91,
    "color1IdPicked": 10,
    "color1SoldQuantity": 1,
    "color2IdPicked": 0,
    "color2SoldQuantity": 0,
    "color3IdPicked": 0,
    "color3SoldQuantity": 0,
    "color4IdPicked": 0,
    "color4SoldQuantity": 0,
    "confimed": false,
    "date": "1742468505190",
    "idArticle": 76,
    "nameArticle": "Caprice Chwingum®",
    "vid": 141
  },
  {
    "clientSoldToItId": 91,
    "color1IdPicked": 74,
    "color1SoldQuantity": 1,
    "color2IdPicked": 0,
    "color2SoldQuantity": 0,
    "color3IdPicked": 0,
    "color3SoldQuantity": 0,
    "color4IdPicked": 0,
    "color4SoldQuantity": 0,
    "confimed": false,
    "date": "1742468595409",
    "idArticle": 754,
    "nameArticle": "Turta®",
    "vid": 142
  },
  {
    "clientSoldToItId": 91,
    "color1IdPicked": 2,
    "color1SoldQuantity": 1,
    "color2IdPicked": 0,
    "color2SoldQuantity": 0,
    "color3IdPicked": 0,
    "color3SoldQuantity": 0,
    "color4IdPicked": 0,
    "color4SoldQuantity": 0,
    "confimed": false,
    "date": "1742468604001",
    "idArticle": 45,
    "nameArticle": "Pino Enrobe®",
    "vid": 143
  },
  {
    "clientSoldToItId": 91,
    "color1IdPicked": 74,
    "color1SoldQuantity": 10,
    "color2IdPicked": 0,
    "color2SoldQuantity": 0,
    "color3IdPicked": 0,
    "color3SoldQuantity": 0,
    "color4IdPicked": 0,
    "color4SoldQuantity": 0,
    "confimed": false,
    "date": "1742468616176",
    "idArticle": 809,
    "nameArticle": "Spi Mat®",
    "vid": 144
  },
  {
    "clientSoldToItId": 91,
    "color1IdPicked": 0,
    "color1SoldQuantity": 0,
    "color2IdPicked": 0,
    "color2SoldQuantity": 0,
    "color3IdPicked": 0,
    "color3SoldQuantity": 0,
    "color4IdPicked": 0,
    "color4SoldQuantity": 0,
    "confimed": false,
    "date": "1742468727422",
    "idArticle": 341,
    "nameArticle": "المسواك صغير Importation®",
    "vid": 145
  },
  {
    "clientSoldToItId": 91,
    "color1IdPicked": 0,
    "color1SoldQuantity": 0,
    "color2IdPicked": 0,
    "color2SoldQuantity": 0,
    "color3IdPicked": 0,
    "color3SoldQuantity": 0,
    "color4IdPicked": 0,
    "color4SoldQuantity": 0,
    "confimed": false,
    "date": "1742468749513",
    "idArticle": 340,
    "nameArticle": "المسواك كبير Importation®",
    "vid": 146
  },
  {
    "clientSoldToItId": 91,
    "color1IdPicked": 8,
    "color1SoldQuantity": 12,
    "color2IdPicked": 0,
    "color2SoldQuantity": 0,
    "color3IdPicked": 0,
    "color3SoldQuantity": 0,
    "color4IdPicked": 0,
    "color4SoldQuantity": 0,
    "confimed": false,
    "date": "1742468757114",
    "idArticle": 341,
    "nameArticle": "المسواك صغير Importation®",
    "vid": 147
  },
  {
    "clientSoldToItId": 91,
    "color1IdPicked": 8,
    "color1SoldQuantity": 6,
    "color2IdPicked": 0,
    "color2SoldQuantity": 0,
    "color3IdPicked": 0,
    "color3SoldQuantity": 0,
    "color4IdPicked": 0,
    "color4SoldQuantity": 0,
    "confimed": false,
    "date": "1742468762199",
    "idArticle": 340,
    "nameArticle": "المسواك كبير Importation®",
    "vid": 148
  },
  {
    "clientSoldToItId": 91,
    "color1IdPicked": 1,
    "color1SoldQuantity": 1,
    "color2IdPicked": 2,
    "color2SoldQuantity": 1,
    "color3IdPicked": 3,
    "color3SoldQuantity": 1,
    "color4IdPicked": 0,
    "color4SoldQuantity": 0,
    "confimed": false,
    "date": "1742468800742",
    "idArticle": 3652,
    "nameArticle": "dorex",
    "vid": 149
  },
  {
    "clientSoldToItId": 91,
    "color1IdPicked": 4,
    "color1SoldQuantity": 1,
    "color2IdPicked": 120,
    "color2SoldQuantity": 1,
    "color3IdPicked": 0,
    "color3SoldQuantity": 0,
    "color4IdPicked": 0,
    "color4SoldQuantity": 0,
    "confimed": false,
    "date": "1742468915050",
    "idArticle": 921,
    "nameArticle": "dove savonn",
    "vid": 150
  },
  {
    "clientSoldToItId": 91,
    "color1IdPicked": 93,
    "color1SoldQuantity": 1,
    "color2IdPicked": 0,
    "color2SoldQuantity": 0,
    "color3IdPicked": 0,
    "color3SoldQuantity": 0,
    "color4IdPicked": 0,
    "color4SoldQuantity": 0,
    "confimed": false,
    "date": "1742469035169",
    "idArticle": 903,
    "nameArticle": "curdon",
    "vid": 151
  }
]